{"3.0.3": ["Francesco Del Duchetto", "fdelduchetto@lincoln.ac.uk"], "3.0.2": ["Francesco Del Duchetto", "fdelduchetto@lincoln.ac.uk"], "3.0.1": ["Francesco Del Duchetto", "fdelduchetto@lincoln.ac.uk"], "2.4.0": ["Francesco Del Duchetto", "fdelduchetto@lincoln.ac.uk"], "2.3.0": ["Francesco Del Duchetto", "fdelduchetto@lincoln.ac.uk"], "2.2.0": ["Francesco Del Duchetto", "fdelduchetto@lincoln.ac.uk"], "2.1.0": ["Francesco Del Duchetto", "fdelduchetto@lincoln.ac.uk"], "2.0.0": ["Francesco Del Duchetto", "fdelduchetto@lincoln.ac.uk"], "1.1.1": ["Francesco Del Duchetto", "fdelduchetto@lincoln.ac.uk"]}